LICENSE
README.md
setup.py
openweathermapsdk/OpenWeatherMap.py
openweathermapsdk/__init__.py
openweathermapsdk.egg-info/PKG-INFO
openweathermapsdk.egg-info/SOURCES.txt
openweathermapsdk.egg-info/dependency_links.txt
openweathermapsdk.egg-info/top_level.txt