Metadata-Version: 2.1
Name: openweathermapsdk
Version: 0.1.0
Summary: An SDK for getting weather and forecast information, using OpenWeatherMap api
Home-page: https://github.com/dasilvactu/openweathermapSDK
Author: Marcus Vinicius da Silva
Author-email: msilva@ice.ufjf.br
License: UNKNOWN
Platform: UNKNOWN
Classifier: Development Status :: 3 - Alpha
Classifier: Intended Audience :: Developers
Classifier: License :: OSI Approved :: MIT License
Classifier: Programming Language :: Python :: 3
Classifier: Programming Language :: Python :: 3.6
Classifier: Programming Language :: Python :: 3.7
Classifier: Programming Language :: Python :: 3.8
Classifier: Programming Language :: Python :: 3.11
License-File: LICENSE
